pyfb_company/__init__.py
pyfb_company/admin.py
pyfb_company/api.py
pyfb_company/apps.py
pyfb_company/forms.py
pyfb_company/models.py
pyfb_company/serializers.py
pyfb_company/urls.py
pyfb_company/views.py
pyfb_company/migrations/0001_initial.py
pyfb_company/migrations/0002_auto_20181210_1131.py
pyfb_company/migrations/0003_auto_20181210_1132.py
pyfb_company/migrations/0004_auto_20181210_1138.py
pyfb_company/migrations/0005_customer_blocking_credit_limit.py
pyfb_company/migrations/0006_auto_20200917_1708.py
pyfb_company/migrations/0007_auto_20201223_0145.py
pyfb_company/migrations/0008_auto_20201223_0759.py
pyfb_company/migrations/0009_auto_20201223_1308.py
pyfb_company/migrations/0010_auto_20201223_1323.py
pyfb_company/migrations/__init__.py
pyfb_company/static/css/pyfb_company.css
pyfb_company/static/js/pyfb_company.js
pyfb_company/templates/base.html
pyfb_company/templates/base.html.py
pyfb_company/templates/pyfb_company/company_detail.html
pyfb_company/templates/pyfb_company/company_detail.html.py
pyfb_company/templates/pyfb_company/company_form.html
pyfb_company/templates/pyfb_company/company_form.html.py
pyfb_company/templates/pyfb_company/company_list.html
pyfb_company/templates/pyfb_company/company_list.html.py
pyfb_company/templates/pyfb_company/companybalancehistory_detail.html
pyfb_company/templates/pyfb_company/companybalancehistory_detail.html.py
pyfb_company/templates/pyfb_company/companybalancehistory_form.html
pyfb_company/templates/pyfb_company/companybalancehistory_form.html.py
pyfb_company/templates/pyfb_company/companybalancehistory_list.html
pyfb_company/templates/pyfb_company/companybalancehistory_list.html.py
pyfb_company/templates/pyfb_company/customer_detail.html
pyfb_company/templates/pyfb_company/customer_detail.html.py
pyfb_company/templates/pyfb_company/customer_form.html
pyfb_company/templates/pyfb_company/customer_form.html.py
pyfb_company/templates/pyfb_company/customer_list.html
pyfb_company-1.3.0.dist-info/DESCRIPTION.rst
pyfb_company-1.3.0.dist-info/METADATA
pyfb_company-1.3.0.dist-info/RECORD
pyfb_company-1.3.0.dist-info/WHEEL
pyfb_company-1.3.0.dist-info/metadata.json
pyfb_company-1.3.0.dist-info/top_level.txt
