Metadata-Version: 2.0
Name: pyfb-company
Version: 1.3.0
Summary: Company package for pyfreebilling application
Home-page: https://www.pyfreebilling.com
Author: Mathias WOLFF
Author-email: mathias@celea.org
License: MIT
Keywords: pyfb-company
Platform: UNKNOWN
Classifier: Development Status :: 5 - Production/Stable
Classifier: Framework :: Django :: 2.2
Classifier: Intended Audience :: Developers
Classifier: License :: OSI Approved :: MIT License
Classifier: Natural Language :: English
Classifier: Programming Language :: Python :: 3.5
Classifier: Programming Language :: Python :: 3.6
Requires-Dist: django-model-utils (>=2.0)
Requires-Dist: django-extensions (>=2.1.3)
Requires-Dist: djangorestframework (>=3.7.7)
Requires-Dist: django-crispy-forms (>=1.7.0)
